Workbook

Sheet チャネル料率
A1: 販売チャネル別 手数料率（目安・要確認）
A2: ※黄色セルは概算です。実際のご契約プラン・カテゴリの料率に必ず書き換えてください（2026年7月時点の一般的な目安）。
A4: チャネル名 | B4: モール手数料率 | C4: 決済手数料率 | D4: 備考
A5: 自社サイト(BASE) | B5: 0.03 | C5: 0.036 | D5: サービス利用料3%+決済3.6%(+40円/件は別途)
A6: 自社サイト(Stripe) | B6: 0 | C6: 0.036 | D6: 決済のみ。集客・広告費は別途かかる
A7: Amazon | B7: 0.15 | C7: 0 | D7: 販売手数料8〜15%(カテゴリ差)。決済は手数料に含む
A8: 楽天市場 | B8: 0.08 | C8: 0.033 | D8: システム利用料+ポイント原資+アフィリ等の概算
A9: Yahoo!ショッピング | B9: 0.03 | C9: 0.035 | D9: ストアポイント原資+キャンペーン原資+決済の概算

Sheet 粗利計算
A1: NETSEA ドロップシッピング 粗利計算シート
A2: 目標粗利率（この値以上を「採用」とする）→ | E2: 0.15 | F2: ◎=目標+5%以上 / ○=目標以上 / △=目標未満 / ×=10%未満
A4: 商品名 | B4: NETSEA商品ID | C4: サプライヤー | D4: 販売チャネル | E4: 販売価格 | F4: 商品原価 | G4: 仕入送料 | H4: モール 手数料率 | I4: 決済 手数料率 | J4: 想定 返品率 | K4: 広告費率 | L4: モール 手数料 | M4: 決済 手数料 | N4: 返品損 | O4: 広告費 | P4: 総コスト | Q4: 粗利額 | R4: 粗利率 | S4: 判定
A5: （記入例）アロマディフューザー 木目調 | B5: 1234567 | C5: 〇〇商事 | D5: 自社サイト(BASE) | E5: 3980 | F5: 1780 | G5: 500 | H5: =IF(D5="","",IFERROR(INDEX(チャネル料率!$B$5:$B$9,MATCH(D5,チャネル料率!$A$5:$A$9,0)),"")) | I5: =IF(D5="","",IFERROR(INDEX(チャネル料率!$C$5:$C$9,MATCH(D5,チャネル料率!$A$5:$A$9,0)),"")) | J5: 0.03 | K5: 0.1 | L5: =IF(E5="","",E5*H5) | M5: =IF(E5="","",E5*I5) | N5: =IF(E5="","",(F5+G5)*J5) | O5: =IF(E5="","",E5*K5) | P5: =IF(E5="","",F5+G5+L5+M5+N5+O5) | Q5: =IF(E5="","",E5-P5) | R5: =IF(E5="","",IFERROR(Q5/E5,"")) | S5: =IF(E5="","",IF(R5>=$E$2+0.05,"◎",IF(R5>=$E$2,"○",IF(R5>=0.1,"△","×"))))
H6: =IF(D6="","",IFERROR(INDEX(チャネル料率!$B$5:$B$9,MATCH(D6,チャネル料率!$A$5:$A$9,0)),"")) | I6: =IF(D6="","",IFERROR(INDEX(チャネル料率!$C$5:$C$9,MATCH(D6,チャネル料率!$A$5:$A$9,0)),"")) | L6: =IF(E6="","",E6*H6) | M6: =IF(E6="","",E6*I6) | N6: =IF(E6="","",(F6+G6)*J6) | O6: =IF(E6="","",E6*K6) | P6: =IF(E6="","",F6+G6+L6+M6+N6+O6) | Q6: =IF(E6="","",E6-P6) | R6: =IF(E6="","",IFERROR(Q6/E6,"")) | S6: =IF(E6="","",IF(R6>=$E$2+0.05,"◎",IF(R6>=$E$2,"○",IF(R6>=0.1,"△","×"))))
H7: =IF(D7="","",IFERROR(INDEX(チャネル料率!$B$5:$B$9,MATCH(D7,チャネル料率!$A$5:$A$9,0)),"")) | I7: =IF(D7="","",IFERROR(INDEX(チャネル料率!$C$5:$C$9,MATCH(D7,チャネル料率!$A$5:$A$9,0)),"")) | L7: =IF(E7="","",E7*H7) | M7: =IF(E7="","",E7*I7) | N7: =IF(E7="","",(F7+G7)*J7) | O7: =IF(E7="","",E7*K7) | P7: =IF(E7="","",F7+G7+L7+M7+N7+O7) | Q7: =IF(E7="","",E7-P7) | R7: =IF(E7="","",IFERROR(Q7/E7,"")) | S7: =IF(E7="","",IF(R7>=$E$2+0.05,"◎",IF(R7>=$E$2,"○",IF(R7>=0.1,"△","×"))))
H8: =IF(D8="","",IFERROR(INDEX(チャネル料率!$B$5:$B$9,MATCH(D8,チャネル料率!$A$5:$A$9,0)),"")) | I8: =IF(D8="","",IFERROR(INDEX(チャネル料率!$C$5:$C$9,MATCH(D8,チャネル料率!$A$5:$A$9,0)),"")) | L8: =IF(E8="","",E8*H8) | M8: =IF(E8="","",E8*I8) | N8: =IF(E8="","",(F8+G8)*J8) | O8: =IF(E8="","",E8*K8) | P8: =IF(E8="","",F8+G8+L8+M8+N8+O8) | Q8: =IF(E8="","",E8-P8) | R8: =IF(E8="","",IFERROR(Q8/E8,"")) | S8: =IF(E8="","",IF(R8>=$E$2+0.05,"◎",IF(R8>=$E$2,"○",IF(R8>=0.1,"△","×"))))
H9: =IF(D9="","",IFERROR(INDEX(チャネル料率!$B$5:$B$9,MATCH(D9,チャネル料率!$A$5:$A$9,0)),"")) | I9: =IF(D9="","",IFERROR(INDEX(チャネル料率!$C$5:$C$9,MATCH(D9,チャネル料率!$A$5:$A$9,0)),"")) | L9: =IF(E9="","",E9*H9) | M9: =IF(E9="","",E9*I9) | N9: =IF(E9="","",(F9+G9)*J9) | O9: =IF(E9="","",E9*K9) | P9: =IF(E9="","",F9+G9+L9+M9+N9+O9) | Q9: =IF(E9="","",E9-P9) | R9: =IF(E9="","",IFERROR(Q9/E9,"")) | S9: =IF(E9="","",IF(R9>=$E$2+0.05,"◎",IF(R9>=$E$2,"○",IF(R9>=0.1,"△","×"))))
H10: =IF(D10="","",IFERROR(INDEX(チャネル料率!$B$5:$B$9,MATCH(D10,チャネル料率!$A$5:$A$9,0)),"")) | I10: =IF(D10="","",IFERROR(INDEX(チャネル料率!$C$5:$C$9,MATCH(D10,チャネル料率!$A$5:$A$9,0)),"")) | L10: =IF(E10="","",E10*H10) | M10: =IF(E10="","",E10*I10) | N10: =IF(E10="","",(F10+G10)*J10) | O10: =IF(E10="","",E10*K10) | P10: =IF(E10="","",F10+G10+L10+M10+N10+O10) | Q10: =IF(E10="","",E10-P10) | R10: =IF(E10="","",IFERROR(Q10/E10,"")) | S10: =IF(E10="","",IF(R10>=$E$2+0.05,"◎",IF(R10>=$E$2,"○",IF(R10>=0.1,"△","×"))))
H11: =IF(D11="","",IFERROR(INDEX(チャネル料率!$B$5:$B$9,MATCH(D11,チャネル料率!$A$5:$A$9,0)),"")) | I11: =IF(D11="","",IFERROR(INDEX(チャネル料率!$C$5:$C$9,MATCH(D11,チャネル料率!$A$5:$A$9,0)),"")) | L11: =IF(E11="","",E11*H11) | M11: =IF(E11="","",E11*I11) | N11: =IF(E11="","",(F11+G11)*J11) | O11: =IF(E11="","",E11*K11) | P11: =IF(E11="","",F11+G11+L11+M11+N11+O11) | Q11: =IF(E11="","",E11-P11) | R11: =IF(E11="","",IFERROR(Q11/E11,"")) | S11: =IF(E11="","",IF(R11>=$E$2+0.05,"◎",IF(R11>=$E$2,"○",IF(R11>=0.1,"△","×"))))
H12: =IF(D12="","",IFERROR(INDEX(チャネル料率!$B$5:$B$9,MATCH(D12,チャネル料率!$A$5:$A$9,0)),"")) | I12: =IF(D12="","",IFERROR(INDEX(チャネル料率!$C$5:$C$9,MATCH(D12,チャネル料率!$A$5:$A$9,0)),"")) | L12: =IF(E12="","",E12*H12) | M12: =IF(E12="","",E12*I12) | N12: =IF(E12="","",(F12+G12)*J12) | O12: =IF(E12="","",E12*K12) | P12: =IF(E12="","",F12+G12+L12+M12+N12+O12) | Q12: =IF(E12="","",E12-P12) | R12: =IF(E12="","",IFERROR(Q12/E12,"")) | S12: =IF(E12="","",IF(R12>=$E$2+0.05,"◎",IF(R12>=$E$2,"○",IF(R12>=0.1,"△","×"))))
H13: =IF(D13="","",IFERROR(INDEX(チャネル料率!$B$5:$B$9,MATCH(D13,チャネル料率!$A$5:$A$9,0)),"")) | I13: =IF(D13="","",IFERROR(INDEX(チャネル料率!$C$5:$C$9,MATCH(D13,チャネル料率!$A$5:$A$9,0)),"")) | L13: =IF(E13="","",E13*H13) | M13: =IF(E13="","",E13*I13) | N13: =IF(E13="","",(F13+G13)*J13) | O13: =IF(E13="","",E13*K13) | P13: =IF(E13="","",F13+G13+L13+M13+N13+O13) | Q13: =IF(E13="","",E13-P13) | R13: =IF(E13="","",IFERROR(Q13/E13,"")) | S13: =IF(E13="","",IF(R13>=$E$2+0.05,"◎",IF(R13>=$E$2,"○",IF(R13>=0.1,"△","×"))))
H14: =IF(D14="","",IFERROR(INDEX(チャネル料率!$B$5:$B$9,MATCH(D14,チャネル料率!$A$5:$A$9,0)),"")) | I14: =IF(D14="","",IFERROR(INDEX(チャネル料率!$C$5:$C$9,MATCH(D14,チャネル料率!$A$5:$A$9,0)),"")) | L14: =IF(E14="","",E14*H14) | M14: =IF(E14="","",E14*I14) | N14: =IF(E14="","",(F14+G14)*J14) | O14: =IF(E14="","",E14*K14) | P14: =IF(E14="","",F14+G14+L14+M14+N14+O14) | Q14: =IF(E14="","",E14-P14) | R14: =IF(E14="","",IFERROR(Q14/E14,"")) | S14: =IF(E14="","",IF(R14>=$E$2+0.05,"◎",IF(R14>=$E$2,"○",IF(R14>=0.1,"△","×"))))
H15: =IF(D15="","",IFERROR(INDEX(チャネル料率!$B$5:$B$9,MATCH(D15,チャネル料率!$A$5:$A$9,0)),"")) | I15: =IF(D15="","",IFERROR(INDEX(チャネル料率!$C$5:$C$9,MATCH(D15,チャネル料率!$A$5:$A$9,0)),"")) | L15: =IF(E15="","",E15*H15) | M15: =IF(E15="","",E15*I15) | N15: =IF(E15="","",(F15+G15)*J15) | O15: =IF(E15="","",E15*K15) | P15: =IF(E15="","",F15+G15+L15+M15+N15+O15) | Q15: =IF(E15="","",E15-P15) | R15: =IF(E15="","",IFERROR(Q15/E15,"")) | S15: =IF(E15="","",IF(R15>=$E$2+0.05,"◎",IF(R15>=$E$2,"○",IF(R15>=0.1,"△","×"))))
H16: =IF(D16="","",IFERROR(INDEX(チャネル料率!$B$5:$B$9,MATCH(D16,チャネル料率!$A$5:$A$9,0)),"")) | I16: =IF(D16="","",IFERROR(INDEX(チャネル料率!$C$5:$C$9,MATCH(D16,チャネル料率!$A$5:$A$9,0)),"")) | L16: =IF(E16="","",E16*H16) | M16: =IF(E16="","",E16*I16) | N16: =IF(E16="","",(F16+G16)*J16) | O16: =IF(E16="","",E16*K16) | P16: =IF(E16="","",F16+G16+L16+M16+N16+O16) | Q16: =IF(E16="","",E16-P16) | R16: =IF(E16="","",IFERROR(Q16/E16,"")) | S16: =IF(E16="","",IF(R16>=$E$2+0.05,"◎",IF(R16>=$E$2,"○",IF(R16>=0.1,"△","×"))))
H17: =IF(D17="","",IFERROR(INDEX(チャネル料率!$B$5:$B$9,MATCH(D17,チャネル料率!$A$5:$A$9,0)),"")) | I17: =IF(D17="","",IFERROR(INDEX(チャネル料率!$C$5:$C$9,MATCH(D17,チャネル料率!$A$5:$A$9,0)),"")) | L17: =IF(E17="","",E17*H17) | M17: =IF(E17="","",E17*I17) | N17: =IF(E17="","",(F17+G17)*J17) | O17: =IF(E17="","",E17*K17) | P17: =IF(E17="","",F17+G17+L17+M17+N17+O17) | Q17: =IF(E17="","",E17-P17) | R17: =IF(E17="","",IFERROR(Q17/E17,"")) | S17: =IF(E17="","",IF(R17>=$E$2+0.05,"◎",IF(R17>=$E$2,"○",IF(R17>=0.1,"△","×"))))
... H34: =IF(D34="","",IFERROR(INDEX(チャネル料率!$B$5:$B$9,MATCH(D34,チャネル料率!$A$5:$A$9,0)),"")) | I34: =IF(D34="","",IFERROR(INDEX(チャネル料率!$C$5:$C$9,MATCH(D34,チャネル料率!$A$5:$A$9,0)),"")) | L34: =IF(E34="","",E34*H34) | M34: =IF(E34="","",E34*I34) | N34: =IF(E34="","",(F34+G34)*J34) | O34: =IF(E34="","",E34*K34) | P34: =IF(E34="","",F34+G34+L34+M34+N34+O34) | Q34: =IF(E34="","",E34-P34) | R34: =IF(E34="","",IFERROR(Q34/E34,"")) | S34: =IF(E34="","",IF(R34>=$E$2+0.05,"◎",IF(R34>=$E$2,"○",IF(R34>=0.1,"△","×"))))
A36: 集計（記入済みのみ） | P36: 平均→ | Q36: =IFERROR(AVERAGE(Q5:Q34),0) | R36: =IFERROR(AVERAGEIF(E5:E34,"<>",R5:R34),0)
P37: 採用件数(○◎)→ | Q37: =COUNTIF(S5:S34,"○")+COUNTIF(S5:S34,"◎")

Sheet 使い方
A1: NETSEA 粗利計算シート — 使い方
A3: 【手順】
A4: 1. 「チャネル料率」タブの黄色セルを、自分の契約プラン・出品カテゴリの実際の料率に書き換える。
A5: 2. 「粗利計算」タブに、NETSEAで見つけた商品を1行ずつ入力する（青字の列だけ）。
A6: 3. 販売チャネルはプルダウンから選択。モール手数料率・決済手数料率は自動で入る（緑字）。
A7: 4. 粗利率と判定（◎○△×）が自動計算される。○以上だけを実際に出品候補にする。
A9: 【色の意味】
A10: 青字 … あなたが手入力する数字
A11: 緑字（斜体）… チャネルから自動で入る料率（触らない）
A12: 黒字 … 自動計算（触らない）
A13: 黄色セル … 契約内容に合わせて必ず確認・書き換える前提値
A15: 【計算式】
... A25: ・料率は2026年7月時点の一般的な目安です。最新の公式情報・RMS/ご契約内容で必ずご確認ください。
